setup.cfg
setup.py
django_orm_profiler/__init__.py
django_orm_profiler/profiler.py
django_orm_profiler.egg-info/PKG-INFO
django_orm_profiler.egg-info/SOURCES.txt
django_orm_profiler.egg-info/dependency_links.txt
django_orm_profiler.egg-info/not-zip-safe
django_orm_profiler.egg-info/requires.txt
django_orm_profiler.egg-info/top_level.txt
django_orm_profiler/core/__init__.py
django_orm_profiler/core/config.py
django_orm_profiler/core/emitter.py
django_orm_profiler/core/exceptions.py
django_orm_profiler/core/logger.py