Metadata-Version: 1.1
Name: django-orm-profiler
Version: 1.0.3
Summary: Django ORM profiler to find redundant and unnecessary queries.
Home-page: https://github.com/klaviyo/django-orm-profiler
Author: Klaviyo
Author-email: community@klaviyo.com
License: MIT
Download-URL: https://github.com/klaviyo/django-orm-profiler/archive/1.0.3.tar.gz
Platform: UNKNOWN
